adafruit_ble_cycling_speed_and_cadence.py
adafruit_circuitpython_ble_cycling_speed_and_cadence-1.1.20.dist-info/licenses/LICENSE
adafruit_circuitpython_ble_cycling_speed_and_cadence-1.1.20.dist-info/METADATA
adafruit_circuitpython_ble_cycling_speed_and_cadence-1.1.20.dist-info/WHEEL
adafruit_circuitpython_ble_cycling_speed_and_cadence-1.1.20.dist-info/top_level.txt
adafruit_circuitpython_ble_cycling_speed_and_cadence-1.1.20.dist-info/RECORD
