Metadata-Version: 2.4
Name: adafruit-circuitpython-ble-cycling-speed-and-cadence
Version: 1.1.20
Summary: BLE Cycling Speed and Cadence Service
Author-email: Adafruit Industries <circuitpython@adafruit.com>
License: MIT
Project-URL: Homepage, https://github.com/adafruit/Adafruit_CircuitPython_BLE_Cycling_Speed_and_Cadence
Keywords: adafruit,blinka,circuitpython,micropython,ble_cycling_speed_and_cadence,ble,cycling,speed,cadence,bicycle,bike
Classifier: Intended Audience :: Developers
Classifier: Topic :: Software Development :: Libraries
Classifier: Topic :: Software Development :: Embedded Systems
Classifier: Topic :: System :: Hardware
Classifier: License :: OSI Approved :: MIT License
Classifier: Programming Language :: Python :: 3
License-File: LICENSE
Requires-Dist: Adafruit-Blinka
Requires-Dist: adafruit-circuitpython-ble
Provides-Extra: optional
Dynamic: license-file
